rrap/__init__.py
rrap/concatenator.py
rrap/controller.py
rrap/indexer.py
rrap/read_recruiter.py
rrap/visualizer.py
rrap-1.3.2.data/data/tests/metaGs/dir_01/ERR864073_toy_R1.fastq
rrap-1.3.2.data/data/tests/metaGs/dir_01/ERR864073_toy_R2.fastq
rrap-1.3.2.data/data/tests/metaGs/dir_01/ERR864077_toy_R1.fastq
rrap-1.3.2.data/data/tests/metaGs/dir_01/ERR864077_toy_R2.fastq
rrap-1.3.2.data/data/tests/metaGs/dir_02/SRR11803378_toy_R1.fastq
rrap-1.3.2.data/data/tests/metaGs/dir_02/SRR11803378_toy_R2.fastq
rrap-1.3.2.data/data/tests/output/allgenomes_cat_val.fna
rrap-1.3.2.data/data/tests/output/total_reads_val.csv
rrap-1.3.2.data/data/tests/output/bam/val/ERR864073.bam
rrap-1.3.2.data/data/tests/output/bam/val/ERR864073.bam.bai
rrap-1.3.2.data/data/tests/output/bam/val/ERR864077.bam
rrap-1.3.2.data/data/tests/output/bam/val/ERR864077.bam.bai
rrap-1.3.2.data/data/tests/output/bam/val/SRR11803378.bam
rrap-1.3.2.data/data/tests/output/bam/val/SRR11803378.bam.bai
rrap-1.3.2.data/data/tests/output/index/val/val.1.bt2
rrap-1.3.2.data/data/tests/output/index/val/val.2.bt2
rrap-1.3.2.data/data/tests/output/index/val/val.3.bt2
rrap-1.3.2.data/data/tests/output/index/val/val.4.bt2
rrap-1.3.2.data/data/tests/output/index/val/val.rev.1.bt2
rrap-1.3.2.data/data/tests/output/index/val/val.rev.2.bt2
rrap-1.3.2.data/data/tests/output/rpkm/val/val_rpkm_log10.csv
rrap-1.3.2.data/data/tests/output/rpkm/val/val_rpkm_noLog.csv
rrap-1.3.2.data/data/tests/output/stats/val/ERR864073.bam.stats
rrap-1.3.2.data/data/tests/output/stats/val/ERR864077.bam.stats
rrap-1.3.2.data/data/tests/output/stats/val/SRR11803378.bam.stats
rrap-1.3.2.data/data/tests/reference/HIMB59.fasta
rrap-1.3.2.data/data/tests/reference/HTCC1062.fasta
rrap-1.3.2.data/scripts/rrap
rrap-1.3.2.data/scripts/rrap_test
rrap-1.3.2.dist-info/LICENSE
rrap-1.3.2.dist-info/METADATA
rrap-1.3.2.dist-info/WHEEL
rrap-1.3.2.dist-info/top_level.txt
rrap-1.3.2.dist-info/RECORD
