Metadata-Version: 2.1
Name: rrap
Version: 1.3.2
Summary: A metagenomic read recruitment data pipeline
Home-page: https://github.com/Kojiconner/rrap_metag_pkg/
Author: Conner Kojima
Author-email: cykojima@usc.edu
License: MIT
Classifier: Programming Language :: Python :: 3
Classifier: License :: OSI Approved :: MIT License
Classifier: Operating System :: OS Independent
Requires-Python: >=3.7.3
License-File: LICENSE
Requires-Dist: joblib (==0.16.0)
Requires-Dist: scikit-learn (==0.23.1)
Requires-Dist: scipy (>=1.5.2)
Requires-Dist: threadpoolctl (==2.1.0)
